manitex/__init__.py
manitex/manitex.py
manitex/manitex.sync-conflict-20230112-103921-X2NEB3V.py
manitex/manitex.sync-conflict-20230112-104024-X2NEB3V.py
manitex/single.py
manitex-0.2.0.dist-info/METADATA
manitex-0.2.0.dist-info/WHEEL
manitex-0.2.0.dist-info/entry_points.txt
manitex-0.2.0.dist-info/top_level.txt
manitex-0.2.0.dist-info/RECORD
