Metadata-Version: 2.1
Name: manitex
Version: 0.2.0
Summary: Generate manifest and bundle for Latex article publication.
Author-email: Serge Rey <sjsrey@gmail.com>
Project-URL: Homepage, https://github.com/sjsrey/manitex
Project-URL: Bug Tracker, https://github.com/sjsrey/manitex/issues
Classifier: Programming Language :: Python :: 3
Classifier: License :: OSI Approved :: MIT License
Classifier: Operating System :: OS Independent
Requires-Python: >=3.7
